token_information/__init__.py
token_information-1.0.0.dist-info/METADATA
token_information-1.0.0.dist-info/WHEEL
token_information-1.0.0.dist-info/entry_points.txt
token_information-1.0.0.dist-info/top_level.txt
token_information-1.0.0.dist-info/RECORD
