Metadata-Version: 2.1
Name: token-information
Version: 1.0.0
Summary: token_information is a Python Package created for scraping discord account data with the use of an account token.
Home-page: https://github.com/spy404/token_information-package
Author: spy404
Author-email: spy404 <spy404.work@gmail.com>
Project-URL: Homepage, https://github.com/spy404/token_information-package
Keywords: spy404,discord,token_information
Classifier: License :: OSI Approved :: MIT License
Classifier: Programming Language :: Python
Classifier: Programming Language :: Python :: 3
Requires-Python: >=3.9
Requires-Dist: requests
Requires-Dist: pystyle
